{
    "episodios": [
        {
            "title": "4x01. Episódio 1",
            "url": [
                "https://animezey16082023.animezey16082023.workers.dev/download.aspx?file=t5M0btj82aEx18W04TIo%2FHD9CAYi1wUjfOivF6Kt4p5WmRbYQFbivMLKbyihN025&expiry=E9oOtmWQV44liM69v44r%2BQ%3D%3D&mac=c320dfb8bdda90a92f276b35bdc442831f63a64fb414d1327ad505ba3ea85bfa"
            ]
        },
        {
            "title": "4x02. Episódio 2",
            "url": [
                "https://animezey16082023.animezey16082023.workers.dev/download.aspx?file=UwQIiBYdlZ9XOLQSAawxhzcxuNGhRd1TIL%2FyVCoQFxtsSYhJuKKPIpb1NdpxS1EA&expiry=qnrr5oCaliifPiZKD52caA%3D%3D&mac=d8f3ad767874cb6e2dd62af0036e71298e1e0d3a5bb068d46f35b014765e36cb"
            ]
        },
        {
            "title": "4x03. Episódio 3",
            "url": [
                "https://animezey16082023.animezey16082023.workers.dev/download.aspx?file=xLn6jsoohla9WEIB2%2F9X0xFNoxzGTGrLhswiBDHV%2FxUorzRNN4aYG7WIjCowv6yi&expiry=MB0%2FjNegoIFa%2FpEHhssbYw%3D%3D&mac=bd2fffef76798d8a2ad8973336344790033fc19260314e484611b359f606e63b"
            ]
        },
        {
            "title": "4x04. Episódio 4",
            "url": [
                "https://animezey16082023.animezey16082023.workers.dev/download.aspx?file=bUDj0Mn%2B95hM%2B9iKXL83MdTzPfUczallzs%2FlVaTWmNKfkhv%2BNKWutk2oniqxo9sM&expiry=CWs%2FwNGnYJDw4Zbgmi%2FcVg%3D%3D&mac=d242e3b60ca9df16663bf2f81766dd19de6877e4b1f3cb1f47f57e07974e96ad"
            ]
        },
        {
            "title": "4x05. Episódio 5",
            "url": [
                "https://animezey16082023.animezey16082023.workers.dev/download.aspx?file=XxZ%2FxGr4obZl63vwrd2GzNp%2Fbxw3mUrwZzpOi4caXbCIbsCn3PF4nMLGVFOlfeAg&expiry=EjUexPKFS41KmxhkSWX%2FMA%3D%3D&mac=e32a8a1a9012d313a5ad33bc9c7fcd8b296c105438813865ba184b12feb04748"
            ]
        },
        {
            "title": "4x06. Episódio 6",
            "url": [
                "https://animezey16082023.animezey16082023.workers.dev/download.aspx?file=5GF3ixWD8k3fvHDBGbsyKPpJh4QC3jGJzqw6yWNggoT0yMLuW9JPZvlCrQlWpxTu&expiry=SXWboDuDwPj0doy4TW7jSQ%3D%3D&mac=57aadb5ca1f13069a300069ae57fdc753de31a7ce26ef293dc6cee0b3b0941fd"
            ]
        },
        {
            "title": "4x07. Episódio 7",
            "url": [
                "https://animezey16082023.animezey16082023.workers.dev/download.aspx?file=QBYGSmgYgkBcfdUNypBdPYhwPT%2FbazGXjGqEwksOeeCOBzlWKbZqcnmSRUDLjhp8&expiry=r8np6M21HZlbYuco87lvUg%3D%3D&mac=fd22beaede84091609cb4671ba50a46c5d7758e15465241545e33ae69d597b0a"
            ]
        },
        {
            "title": "4x08. Episódio 8",
            "url": [
                "https://animezey16082023.animezey16082023.workers.dev/download.aspx?file=exwzSct0nKA0oHlPD%2BX7%2F8eVl540W9ae9s0xP621fmkQty2jmyBkXno5rrc%2BqTTc&expiry=1kphy2ZrG5%2Btd1VNeQo1Lw%3D%3D&mac=d787cd4bb4c20f74b29f83f905e4c70f4974d23812ccbe8a2588abb94fac1e69"
            ]
        },
        {
            "title": "4x09. Episódio 9",
            "url": [
                "https://animezey16082023.animezey16082023.workers.dev/download.aspx?file=xmv3uwgHlXbq0N1BQ7SVJwj0e0JBxZKuFcjAr%2FnAp%2F32IuKvpXPlVAlXqkptCD%2F4&expiry=ncxlXLFtk4O3cW1LxQ1yow%3D%3D&mac=ffd43eb9d6b8159608d63e560284756f9b83375cd984de1fcba1fd8fd237414a"
            ]
        },
        {
            "title": "4x010. Episódio 10",
            "url": [
                "https://animezey16082023.animezey16082023.workers.dev/download.aspx?file=e%2FVpHxapixQkwW2LmAT9A84XCXm%2BOPPsXwdN9%2Fj0i854a3yTNSvf0U4ntSUvJ6pg&expiry=pO2%2BmWseAQRi56MIoyStDA%3D%3D&mac=dcdd52b88e9e9e6642a8dc2609cdedac53198217d67801ca9110197211632be3"
            ]
        }
    ]
}