{
    "episodios": [
        {
            "title": "01. Caminhos Cruzados",
            "url": [
                "plugin://plugin.video.elementum/play?uri=magnet:?xt=urn:btih:62a2033edebfec9c1224bce83e3c028fa66770fb"
            ],
            "rating": 4.2,
            "synopsis": "Após uma tragédia familiar, o agente especial Tom Brandis é forçado a liderar uma unidade especial que investiga uma série de roubos.",
            "runtime": 66,
            "poster": "https://image.tmdb.org/t/p/original/yyOAoNHDBnAJrtlq6RVC8citDeb.jpg"
        },
        {
            "title": "02. Declaração Familiar",
            "url": [
                "plugin://plugin.video.elementum/play?uri=magnet:?xt=urn:btih:2ea6463e643c9320b7c97ee8b0b392fdbc89927b"
            ],
            "rating": 5.3,
            "synopsis": "Enquanto a família de Tom se prepara para uma audiência judicial, Robbie enfrenta um dilema e Maeve toma uma decisão crítica.",
            "runtime": 63,
            "poster": "https://image.tmdb.org/t/p/original/ftBHssFPie3KEurGcP94r98tbo8.jpg"
        },
        {
            "title": "03. Ninguém É Mais Forte Que o Perdão",
            "url": [
                "plugin://plugin.video.elementum/play?uri=magnet:?xt=urn:btih:e60bf44c75e06fce057880bb85fbf1dabbee6d1e"
            ],
            "rating": 5.6,
            "synopsis": "Enquanto Robbie e Cliff tentam encontrar um comprador em potencial, Tom e Grasso se abrem com os Corações Negros, e Aleah e Lizzie interrogam os antigos colegas de trabalho de Peaches. Uma operação policial leva Tom a uma revelação chocante.",
            "runtime": 65,
            "poster": "https://image.tmdb.org/t/p/original/2VJRSZImHgC4wSz9zbwv1dg12zd.jpg"
        },
        {
            "title": "04. Episódio 4",
            "url": [
                "plugin://plugin.video.elementum/play?uri=magnet:?xt=urn:btih:"
            ],
            "rating": 0.0,
            "synopsis": "",
            "runtime": 64,
            "poster": "https://image.tmdb.org/t/p/original/nTYwczFpMYPL4mfX5fEeskd3jQC.jpg"
        },
        {
            "title": "05. Episódio 5",
            "url": [
                "plugin://plugin.video.elementum/play?uri=magnet:?xt=urn:btih:"
            ],
            "rating": 0.0,
            "synopsis": "",
            "runtime": 0,
            "poster": ""
        },
        {
            "title": "06. Episódio 6",
            "url": [
                "plugin://plugin.video.elementum/play?uri=magnet:?xt=urn:btih:"
            ],
            "rating": 0.0,
            "synopsis": "",
            "runtime": 0,
            "poster": ""
        },
        {
            "title": "07. Episódio 7",
            "url": [
                "plugin://plugin.video.elementum/play?uri=magnet:?xt=urn:btih:"
            ],
            "rating": 0.0,
            "synopsis": "",
            "runtime": 0,
            "poster": ""
        }
    ]

}
