{
    "episodios": [
        {
            "title": "01. É preciso ter fé",
            "url": [
                "plugin://plugin.video.elementum/play?uri=magnet:?xt=urn:btih:e81bed2f2729555e6e65cf187f8f81f3011a4fe1(EP 01)"
            ],
            "rating": 10.0,
            "synopsis": "Babalwa é uma mãe dedicada que se envolve em uma situação impossível quando a saúde da filha se complica, e acaba entrando em um pacto que vai atrapalhar sua vida.",
            "runtime": 53,
            "poster": "https://image.tmdb.org/t/p/original/qqFN11GnDxwAbxVl7FNSSnvLBN0.jpg"
        },
        {
            "title": "02. Informante",
            "url": [
                "plugin://plugin.video.elementum/play?uri=magnet:?xt=urn:btih:e81bed2f2729555e6e65cf187f8f81f3011a4fe1(EP 02)"
            ],
            "rating": 0.0,
            "synopsis": "A tentativa de assalto de Babalwa dá errado e chama a atenção de um policial corrupto. A iniciativa de Zweli gera conflito com Baba G.",
            "runtime": 41,
            "poster": "https://image.tmdb.org/t/p/original/v2DShrzStP0WG2H98qq3ylRLLW2.jpg"
        },
        {
            "title": "03. Santos e pecadores",
            "url": [
                "plugin://plugin.video.elementum/play?uri=magnet:?xt=urn:btih:e81bed2f2729555e6e65cf187f8f81f3011a4fe1(EP 03)"
            ],
            "rating": 0.0,
            "synopsis": "A luta de Babalwa para encobrir seus rastros gera uma tentativa de chantagem. Zweli ajuda a ex-policial a reunir uma equipe inesperada para um novo assalto.",
            "runtime": 52,
            "poster": "https://image.tmdb.org/t/p/original/qyD3tUMKIhTqQSv1snfklGh96i5.jpg"
        },
        {
            "title": "04. Sodoma e Gomorra",
            "url": [
                "plugin://plugin.video.elementum/play?uri=magnet:?xt=urn:btih:e81bed2f2729555e6e65cf187f8f81f3011a4fe1(EP 04)"
            ],
            "rating": 0.0,
            "synopsis": "Ao planejar o assalto, Babalwa e o grupo chegam à conclusão de que precisam roubar os equipamentos necessários da polícia e de criminosos.",
            "runtime": 40,
            "poster": "https://image.tmdb.org/t/p/original/6MkN6o7xRD7EZDm3UfIzPv5kmZa.jpg"
        },
        {
            "title": "05. Judas Iscariotes",
            "url": [
                "plugin://plugin.video.elementum/play?uri=magnet:?xt=urn:btih:e81bed2f2729555e6e65cf187f8f81f3011a4fe1(EP 05)"
            ],
            "rating": 0.0,
            "synopsis": "Kat interroga Zweli de forma violenta, e Babalwa explora um ponto fraco para tirá-lo da sua cola. O dia do assalto se aproxima, e Lungile fica desconfiado.",
            "runtime": 45,
            "poster": "https://image.tmdb.org/t/p/original/ai1JoUDZhDJA2YBVegBlR3sfKF1.jpg"
        },
        {
            "title": "06. Iron Watch",
            "url": [
                "plugin://plugin.video.elementum/play?uri=magnet:?xt=urn:btih:e81bed2f2729555e6e65cf187f8f81f3011a4fe1(EP 06)"
            ],
            "rating": 0.0,
            "synopsis": "Kat vai ao evento beneficente de Palesa mesmo sem convite. O assalto começa, mas uma série de imprevistos ameaça arruinar tudo.",
            "runtime": 46,
            "poster": "https://image.tmdb.org/t/p/original/uzuRuvVnkOOA2iJiFMTGrHY3NPV.jpg"
        }
    ]
}